mqtt_publish/__init__.py
mqtt_publish/__main__.py
mqtt_publish/bin/__init__.py
mqtt_publish/bin/mqtt_publish.py
mqtt_publish-1.0.dist-info/METADATA
mqtt_publish-1.0.dist-info/WHEEL
mqtt_publish-1.0.dist-info/entry_points.txt
mqtt_publish-1.0.dist-info/top_level.txt
mqtt_publish-1.0.dist-info/RECORD
