Metadata-Version: 2.1
Name: mqtt-publish
Version: 1.0
Summary: A command line utility for quickly publishing a single MQTT message.
Home-page: https://github.com/Terrabits/mqtt_publish
Author: Nick Lalic
Author-email: nick.lalic@gmail.com
License: UNKNOWN
Keywords: MQTT IoT
Platform: UNKNOWN
Classifier: Development Status :: 4 - Beta
Classifier: Environment :: Console
Classifier: Operating System :: MacOS :: MacOS X
Classifier: Operating System :: Microsoft :: Windows
Classifier: Operating System :: POSIX
Classifier: Operating System :: Unix
Classifier: Intended Audience :: Developers
Classifier: License :: Other/Proprietary License
Classifier: Programming Language :: Python :: 3.6
Classifier: Programming Language :: Python :: 3.7
Requires-Dist: paho-mqtt
